genra/__init__.py
genra/chm/__init__.py
genra/chm/chem.py
genra/chm/viz.py
genra/rax/__init__.py
genra/rax/skl/__init__.py
genra/rax/skl/binary.py
genra/rax/skl/cls.py
genra/rax/skl/hybrid.py
genra/rax/skl/reg.py
genra/rax/viz/__init__.py
genra/rax/viz/nn.py
genra/utl/__init__.py
genra/utl/ixml.py
genra/utl/svg.py
src/__init__.py
tests/__init__.py
tests/test_genra.py
tests/test_hybrid.py
genra-0.2.3.dist-info/AUTHORS.rst
genra-0.2.3.dist-info/LICENSE
genra-0.2.3.dist-info/METADATA
genra-0.2.3.dist-info/WHEEL
genra-0.2.3.dist-info/top_level.txt
genra-0.2.3.dist-info/RECORD
