Metadata-Version: 2.1
Name: genra
Version: 0.2.3
Summary: Generalised Read Across (GenRA) in Python
Home-page: https://github.com/i-shah/genra-py
Author: Imran Shah
License: MIT
Keywords: genra
Classifier: Development Status :: 2 - Pre-Alpha
Classifier: Intended Audience :: Developers
Classifier: License :: OSI Approved :: MIT License
Classifier: Natural Language :: English
Classifier: Programming Language :: Python :: 3
License-File: LICENSE
License-File: AUTHORS.rst
Requires-Dist: numpy
Requires-Dist: scipy
Requires-Dist: scikit-learn
Requires-Dist: lxml
